.DS_Store
prime_numbers_r/__init__.py
prime_numbers_r/prime_numbers_r.py
prime_numbers_r-0.0.4.dist-info/LICENSE.txt
prime_numbers_r-0.0.4.dist-info/METADATA
prime_numbers_r-0.0.4.dist-info/WHEEL
prime_numbers_r-0.0.4.dist-info/top_level.txt
prime_numbers_r-0.0.4.dist-info/RECORD
